weak_annotators/__init__.py
weak_annotators/base_extractor.py
weak_annotators/flair_extractor.py
weak_annotators/medalpaca_extractor.py
weak_annotators/model_registry.py
weak_annotators/universal_ner_extractor.py
weak_annotators/version.py
weak_annotators/templates/__init__.py
weak_annotators/templates/conversation.py
weak_annotators/utils/__init__.py
weak_annotators/utils/type_utils.py
weak_annotators-0.0.1.dist-info/METADATA
weak_annotators-0.0.1.dist-info/WHEEL
weak_annotators-0.0.1.dist-info/top_level.txt
weak_annotators-0.0.1.dist-info/RECORD
