Metadata-Version: 2.1
Name: weak-annotators
Version: 0.0.1
Summary: Weak annotators for information extraction (NER)
Home-page: https://github.com/imvladikon/weak_annotators
Author: Vladimir Gurevich
Classifier: Programming Language :: Python :: 3
Classifier: Topic :: Scientific/Engineering
Requires-Python: >=3.9
Requires-Dist: tokenizers
Requires-Dist: accelerate
Requires-Dist: datasets
Requires-Dist: spacy
Requires-Dist: spacy-transformers
Requires-Dist: spacy-experimental
Requires-Dist: transformers
Requires-Dist: sentence-transformers
Requires-Dist: vllm
Requires-Dist: pytextspan
Requires-Dist: flair
Requires-Dist: jinja2
